mcp_ical/__init__.py
mcp_ical/ical.py
mcp_ical/models.py
mcp_ical/server.py
iflow_mcp_mcp_ical-0.1.0.dist-info/METADATA
iflow_mcp_mcp_ical-0.1.0.dist-info/WHEEL
iflow_mcp_mcp_ical-0.1.0.dist-info/entry_points.txt
iflow_mcp_mcp_ical-0.1.0.dist-info/licenses/LICENSE
iflow_mcp_mcp_ical-0.1.0.dist-info/RECORD
