Metadata-Version: 2.4
Name: iflow-mcp_mcp-ical
Version: 0.1.0
Summary: A Model Context Protocol server providing tools for CRUD operations for the mac-os calendar
License-File: LICENSE
Requires-Python: >=3.12
Requires-Dist: loguru>=0.7.3
Requires-Dist: mcp[cli]>=1.2.1
Requires-Dist: pyobjc>=11.0
